simplified/AdvannceActivities.py
simplified/CommonActivities.py
simplified/__init__.py
simplified/simplifiedai/IdentifyLocators.py
simplified/simplifiedai/__init__.py
simplified/simplifiedreport/__init__.py
selenium_simplified-0.18.dist-info/METADATA
selenium_simplified-0.18.dist-info/WHEEL
selenium_simplified-0.18.dist-info/top_level.txt
selenium_simplified-0.18.dist-info/RECORD
