Metadata-Version: 2.1
Name: selenium-simplified
Version: 0.18
Summary: A free, open-source web automation library for the Chrome browser using Selenium Python
Home-page: https://github.com/raajrajnish/SeleniumSimplified.git
Author: rajnish kumar
Author-email: raajrajnish@gmail.com
Classifier: Programming Language :: Python :: 3
Classifier: License :: OSI Approved :: MIT License
Classifier: Operating System :: OS Independent
Requires-Dist: selenium
Requires-Dist: bs4
